albanian_tools/__init__.py
albanian_tools/albanian_tools.py
albanian_tools/utils/__init__.py
albanian_tools/utils/functions.py
albanian_tools-0.0.16.dist-info/LICENSE
albanian_tools-0.0.16.dist-info/METADATA
albanian_tools-0.0.16.dist-info/WHEEL
albanian_tools-0.0.16.dist-info/top_level.txt
albanian_tools-0.0.16.dist-info/RECORD
