Metadata-Version: 2.1
Name: albanian_tools
Version: 0.0.16
Summary: A small package for working with Albanian language texts.
Author-email: Bleron Limani <bleroni@example.com>
Project-URL: Homepage, https://github.com/bleroni/albanian_tools
Project-URL: Issues, https://github.com/bleroni/albanian_tools/issues
Classifier: Programming Language :: Python :: 3
Classifier: License :: OSI Approved :: MIT License
Classifier: Operating System :: OS Independent
Requires-Python: >=3.8.19
License-File: LICENSE
